pycolorama/__init__.py
pycolorama/pycolorama.py
pycolorama-0.7.dist-info/METADATA
pycolorama-0.7.dist-info/WHEEL
pycolorama-0.7.dist-info/top_level.txt
pycolorama-0.7.dist-info/RECORD
