Metadata-Version: 2.1
Name: pycolorama
Version: 0.7
Summary: A simple color module to handle RGB and BGR format more easily
Home-page: https://github.com/ooMakeIToo/pycolorama/
Author: Jay
Author-email: jay.temporary._removethispart_@gmail.com
License: UNKNOWN
Project-URL: Bug Tracker, https://github.com/ooMakeIToo/pycolorama/issues
Platform: UNKNOWN
Classifier: Programming Language :: Python :: 2
Classifier: Operating System :: OS Independent
Requires-Python: >=2.7
